aircursor/__init__.py
aircursor/__main__.py
aircursor/airmouse.py
aircursor/app.py
aircursor/server.py
aircursor/templates/index.html
aircursor-1.0.6.dist-info/licenses/LICENSE
aircursor-1.0.6.dist-info/METADATA
aircursor-1.0.6.dist-info/WHEEL
aircursor-1.0.6.dist-info/entry_points.txt
aircursor-1.0.6.dist-info/top_level.txt
aircursor-1.0.6.dist-info/RECORD
