Metadata-Version: 2.4
Name: aircursor
Version: 1.0.6
Summary: Remote mouse control server with web interface and REST API
Author-email: NiqueWrld <niquewrld@outlook.com>
Project-URL: Homepage, https://github.com/NiqueWrld/AirCursor
Project-URL: Repository, https://github.com/NiqueWrld/AirCursor
Project-URL: Issues, https://github.com/NiqueWrld/AirCursor/issues
Project-URL: Documentation, https://github.com/NiqueWrld/AirCursor#readme
Keywords: flask,mouse,automation,remote,control,REST,qr,web
Classifier: Development Status :: 4 - Beta
Classifier: Intended Audience :: Developers
Classifier: Intended Audience :: End Users/Desktop
Classifier: Topic :: System :: Hardware
Classifier: Topic :: Internet :: WWW/HTTP :: HTTP Servers
Classifier: Topic :: Desktop Environment
Classifier: Programming Language :: Python :: 3
Classifier: Programming Language :: Python :: 3.9
Classifier: Programming Language :: Python :: 3.10
Classifier: Programming Language :: Python :: 3.11
Classifier: Programming Language :: Python :: 3.12
Classifier: License :: OSI Approved :: MIT License
Classifier: Operating System :: OS Independent
Requires-Python: >=3.9
License-File: LICENSE
Requires-Dist: Flask<4,>=3.0.3
Requires-Dist: flask-cors<5,>=4.0.1
Requires-Dist: pyautogui==0.9.54
Requires-Dist: qrcode[pil]==7.4.2
Requires-Dist: pillow>=9.2.0
Requires-Dist: PyScreeze>=0.1.30
Requires-Dist: PyTweening>=1.0.4
Requires-Dist: mouseinfo>=0.1.3
Requires-Dist: pymsgbox>=1.0.9
Requires-Dist: pygetwindow>=0.0.9
Requires-Dist: pyrect>=0.2.0
Dynamic: license-file
